bitwarden_simple_cli/Bitwarden.py
bitwarden_simple_cli/CliSimple.py
bitwarden_simple_cli/CliSimple_test.py
bitwarden_simple_cli/__init__.py
bitwarden_simple_cli/__main__.py
bitwarden_simple_cli/__version__.py
bitwarden_simple_cli/enums/CipherType.py
bitwarden_simple_cli/enums/EncryptionType.py
bitwarden_simple_cli/enums/FieldType.py
bitwarden_simple_cli/enums/__init__.py
bitwarden_simple_cli/exceptions/ManagedException.py
bitwarden_simple_cli/exceptions/__init__.py
bitwarden_simple_cli/models/__init__.py
bitwarden_simple_cli/models/api/FieldApi.py
bitwarden_simple_cli/models/api/LoginApi.py
bitwarden_simple_cli/models/api/__init__.py
bitwarden_simple_cli/models/data/CipherData.py
bitwarden_simple_cli/models/data/FieldData.py
bitwarden_simple_cli/models/data/LoginData.py
bitwarden_simple_cli/models/data/__init__.py
bitwarden_simple_cli/models/domain/Cipher.py
bitwarden_simple_cli/models/domain/CipherString.py
bitwarden_simple_cli/models/domain/Cipher_test.py
bitwarden_simple_cli/models/domain/DecryptParameters.py
bitwarden_simple_cli/models/domain/DomainBase.py
bitwarden_simple_cli/models/domain/Field.py
bitwarden_simple_cli/models/domain/Login.py
bitwarden_simple_cli/models/domain/LoginUri.py
bitwarden_simple_cli/models/domain/SymmetricCryptoKey.py
bitwarden_simple_cli/models/domain/SymmetricCryptoKey_test.py
bitwarden_simple_cli/models/domain/__init__.py
bitwarden_simple_cli/models/response/BaseResponse.py
bitwarden_simple_cli/models/response/BaseResponse_test.py
bitwarden_simple_cli/models/response/CipherResponse.py
bitwarden_simple_cli/models/response/CipherResponse_test.py
bitwarden_simple_cli/models/response/__init__.py
bitwarden_simple_cli/services/CipherService.py
bitwarden_simple_cli/services/CipherService_test.py
bitwarden_simple_cli/services/ContainerService.py
bitwarden_simple_cli/services/ContainerService_test.py
bitwarden_simple_cli/services/CryptoService.py
bitwarden_simple_cli/services/CryptoService_test.py
bitwarden_simple_cli-1.3.1.dist-info/LICENSE
bitwarden_simple_cli-1.3.1.dist-info/METADATA
bitwarden_simple_cli-1.3.1.dist-info/WHEEL
bitwarden_simple_cli-1.3.1.dist-info/entry_points.txt
bitwarden_simple_cli-1.3.1.dist-info/top_level.txt
bitwarden_simple_cli-1.3.1.dist-info/RECORD
