Metadata-Version: 2.1
Name: bitwarden-simple-cli
Version: 1.3.1
Summary: Simple bitwarden CLI written in Python to list and decrypt secrets
Home-page: https://github.com/mickaelperrin/bitwarden-decrypt-cli
Author: Mickaël Perrin
Author-email: dev@mickaelperrin.fr
License: GPLv3
Keywords: bitwarden cli password secrets
Platform: UNKNOWN
Classifier: License :: OSI Approved :: GNU General Public License v3 or later (GPLv3+)
Classifier: Development Status :: 4 - Beta
Classifier: Environment :: Console
Classifier: Intended Audience :: Information Technology
Classifier: Natural Language :: French
Classifier: Topic :: Security
Classifier: Topic :: Security :: Cryptography
Classifier: Topic :: Utilities
Classifier: Programming Language :: Python
Classifier: Programming Language :: Python :: 3
Classifier: Programming Language :: Python :: 3.7
Classifier: Programming Language :: Python :: Implementation :: CPython
Classifier: Programming Language :: Python :: Implementation :: PyPy
Requires-Python: >=3.7.0
Requires-Dist: asn1crypto (==0.24.0)
Requires-Dist: cffi (==1.12.2)
Requires-Dist: cryptography (==2.6.1)
Requires-Dist: pycparser (==2.19)
